nkunyim_util/__init__.py
nkunyim_util/apps.py
nkunyim_util/authentication.py
nkunyim_util/command.py
nkunyim_util/context.py
nkunyim_util/middleware.py
nkunyim_util/permisisons.py
nkunyim_util/api/__init__.py
nkunyim_util/api/nkunyim_api_client.py
nkunyim_util/auth/__init__.py
nkunyim_util/auth/mixins.py
nkunyim_util/bags/view_bag.py
nkunyim_util/caches/__init__.py
nkunyim_util/caches/account_cache.py
nkunyim_util/caches/application_cache.py
nkunyim_util/caches/cache_manager.py
nkunyim_util/caches/location_cache.py
nkunyim_util/caches/nation_cache.py
nkunyim_util/caches/user_agent_cache.py
nkunyim_util/commands/authorize_command.py
nkunyim_util/commands/delete_command.py
nkunyim_util/commands/refresh_command.py
nkunyim_util/commands/revoke_command.py
nkunyim_util/commands/token_command.py
nkunyim_util/commands/userinfo_command.py
nkunyim_util/encryption/__init__.py
nkunyim_util/encryption/aes_encryption.py
nkunyim_util/encryption/rsa_encryption.py
nkunyim_util/management/commands/commands.py
nkunyim_util/management/commands/datax.py
nkunyim_util/management/commands/migrations.py
nkunyim_util/management/commands/template.py
nkunyim_util/messages/email_message.py
nkunyim_util/messages/sms_message.py
nkunyim_util/models/__init__.py
nkunyim_util/models/account_model.py
nkunyim_util/models/application_model.py
nkunyim_util/models/constants.py
nkunyim_util/models/context_model.py
nkunyim_util/models/location_model.py
nkunyim_util/models/logging_model.py
nkunyim_util/models/message_model.py
nkunyim_util/models/nation_model.py
nkunyim_util/models/oauth2_model.py
nkunyim_util/models/page_model.py
nkunyim_util/models/session_model.py
nkunyim_util/models/sms_model.py
nkunyim_util/models/token_model.py
nkunyim_util/models/user_agent_model.py
nkunyim_util/models/user_model.py
nkunyim_util/models/userinfo_model.py
nkunyim_util/services/__init__.py
nkunyim_util/services/account_service.py
nkunyim_util/services/application_service.py
nkunyim_util/services/context_service.py
nkunyim_util-0.5.8.dist-info/METADATA
nkunyim_util-0.5.8.dist-info/WHEEL
nkunyim_util-0.5.8.dist-info/licenses/LICENSE
nkunyim_util-0.5.8.dist-info/RECORD
