Metadata-Version: 2.4
Name: nkunyim_util
Version: 0.5.8
Summary: Nkunyim utilities package
Project-URL: Homepage, https://github.com/nkunyim/nkunyim_util
Project-URL: Issues, https://github.com/nkunyim/nkunyim_util/issues
Author-email: Enoch Enchill <et.enchill@gmail.com>
License-Expression: Apache-2.0
License-File: LICENSE
Classifier: Operating System :: OS Independent
Classifier: Programming Language :: Python :: 3
Requires-Python: >=3.9
Requires-Dist: cryptography
Requires-Dist: django
Requires-Dist: djangorestframework
Requires-Dist: pydantic
Requires-Dist: requests
Requires-Dist: ua-parser
Requires-Dist: user-agents
